flowllm/__init__.py
flowllm/main.py
flowllm/config/__init__.py
flowllm/config/config_parser.py
flowllm/config/default.yaml
flowllm/config/search.yaml
flowllm/core/__init__.py
flowllm/core/application.py
flowllm/core/context/__init__.py
flowllm/core/context/base_context.py
flowllm/core/context/flow_context.py
flowllm/core/context/prompt_handler.py
flowllm/core/context/registry.py
flowllm/core/context/service_context.py
flowllm/core/embedding_model/__init__.py
flowllm/core/embedding_model/base_embedding_model.py
flowllm/core/embedding_model/openai_compatible_embedding_model.py
flowllm/core/enumeration/__init__.py
flowllm/core/enumeration/chunk_enum.py
flowllm/core/enumeration/http_enum.py
flowllm/core/enumeration/registry_enum.py
flowllm/core/enumeration/role.py
flowllm/core/flow/__init__.py
flowllm/core/flow/base_flow.py
flowllm/core/flow/base_tool_flow.py
flowllm/core/flow/cmd_flow.py
flowllm/core/flow/expression_tool_flow.py
flowllm/core/llm/__init__.py
flowllm/core/llm/base_llm.py
flowllm/core/llm/lite_llm.py
flowllm/core/llm/openai_compatible_llm.py
flowllm/core/op/__init__.py
flowllm/core/op/base_async_op.py
flowllm/core/op/base_async_tool_op.py
flowllm/core/op/base_mcp_op.py
flowllm/core/op/base_op.py
flowllm/core/op/base_ray_op.py
flowllm/core/op/parallel_op.py
flowllm/core/op/sequential_op.py
flowllm/core/schema/__init__.py
flowllm/core/schema/flow_request.py
flowllm/core/schema/flow_response.py
flowllm/core/schema/flow_stream_chunk.py
flowllm/core/schema/message.py
flowllm/core/schema/service_config.py
flowllm/core/schema/tool_call.py
flowllm/core/schema/vector_node.py
flowllm/core/service/__init__.py
flowllm/core/service/base_service.py
flowllm/core/service/cmd_service.py
flowllm/core/service/http_service.py
flowllm/core/service/mcp_service.py
flowllm/core/storage/__init__.py
flowllm/core/storage/cache_handler.py
flowllm/core/token/__init__.py
flowllm/core/token/base_token.py
flowllm/core/token/huggingface_token.py
flowllm/core/token/openai_token.py
flowllm-0.2.0.9.dist-info/licenses/LICENSE
flowllm-0.2.0.9.dist-info/METADATA
flowllm-0.2.0.9.dist-info/WHEEL
flowllm-0.2.0.9.dist-info/entry_points.txt
flowllm-0.2.0.9.dist-info/top_level.txt
flowllm-0.2.0.9.dist-info/RECORD
