Metadata-Version: 2.4
Name: flowllm
Version: 0.2.0.9
Summary: FlowLLM: Simplifying LLM-based HTTP/MCP Service Development
Author-email: "jinli.yl" <jinli.yl@alibaba-inc.com>
License:                                  Apache License
Project-URL: Homepage, https://github.com/flowllm-ai/flowllm
Project-URL: Documentation, https://flowllm-ai.github.io/flowllm/
Project-URL: Repository, https://github.com/flowllm-ai/flowllm
Keywords: llm,ai,flow,framework,openai,chatgpt,language-model,mcp,http
Classifier: Development Status :: 4 - Beta
Classifier: Intended Audience :: Developers
Classifier: Intended Audience :: Science/Research
Classifier: License :: OSI Approved :: Apache Software License
Classifier: Operating System :: OS Independent
Classifier: Programming Language :: Python :: 3
Classifier: Programming Language :: Python :: 3.10
Classifier: Topic :: Scientific/Engineering :: Artificial Intelligence
Classifier: Topic :: Software Development :: Libraries :: Python Modules
Classifier: Topic :: Software Development :: Libraries :: Application Frameworks
Classifier: Typing :: Typed
Requires-Python: >=3.10
License-File: LICENSE
Requires-Dist: dashscope>=1.13.0
Requires-Dist: fastapi>=0.104.0
Requires-Dist: fastmcp>=0.1.0
Requires-Dist: httpx>=0.25.0
Requires-Dist: loguru>=0.7.0
Requires-Dist: numpy>=1.24.0
Requires-Dist: pandas>=2.0.0
Requires-Dist: openai>=1.3.0
Requires-Dist: pydantic>=2.0.0
Requires-Dist: PyYAML>=6.0.0
Requires-Dist: requests>=2.31.0
Requires-Dist: tqdm>=4.66.0
Requires-Dist: urllib3>=2.0.0
Requires-Dist: uvicorn[standard]>=0.23.0
Requires-Dist: pyfiglet>=0.8.0
Requires-Dist: rich>=13.5.0
Requires-Dist: pathspec>=0.12.1
Requires-Dist: litellm>=1.0.0
Requires-Dist: tavily-python>=0.2.0
Provides-Extra: dev
Requires-Dist: pytest>=8.4.2; extra == "dev"
Requires-Dist: pytest_asyncio>=1.2.0; extra == "dev"
Requires-Dist: pre-commit; extra == "dev"
Requires-Dist: mkdocs-shadcn; extra == "dev"
Requires-Dist: pipreqs; extra == "dev"
Provides-Extra: reme
Requires-Dist: elasticsearch>=8.10.0; extra == "reme"
Requires-Dist: chromadb>=0.4.0; extra == "reme"
Requires-Dist: qdrant_client>=1.15.1; extra == "reme"
Requires-Dist: pgvector>=0.4.2; extra == "reme"
Provides-Extra: fin
Requires-Dist: akshare>=1.9.0; extra == "fin"
Requires-Dist: crawl4ai>=0.7.4; extra == "fin"
Provides-Extra: token
Requires-Dist: transformers>=4.35.0; extra == "token"
Requires-Dist: tiktoken>=0.5.0; extra == "token"
Provides-Extra: skill
Provides-Extra: full
Requires-Dist: flowllm[dev,fin,reme,skill,token]; extra == "full"
Dynamic: license-file
